charsay/__init__.py
charsay/charsay.py
charsay/content.py
charsay/speechbubble.py
charsay-0.1.33.dist-info/LICENSE.md
charsay-0.1.33.dist-info/METADATA
charsay-0.1.33.dist-info/WHEEL
charsay-0.1.33.dist-info/top_level.txt
charsay-0.1.33.dist-info/RECORD
