Metadata-Version: 2.2
Name: charsay
Version: 0.1.33
Summary: A simple Python package that generates ASCII art of characters saying a given string.
Home-page: https://github.com/kish-0/charsay
Author: Kishan S
Author-email: senthilkumarkishan@gmail.com
License: MIT
Classifier: Programming Language :: Python :: 3
Classifier: License :: OSI Approved :: MIT License
Classifier: Operating System :: OS Independent
License-File: LICENSE.md
Dynamic: author
Dynamic: author-email
Dynamic: classifier
Dynamic: description
Dynamic: description-content-type
Dynamic: home-page
Dynamic: license
Dynamic: summary
